README.md
setup.py
csrc/conv1d_gnm.cpp
csrc/conv1d_gnm_kernel.cu
csrc/denoise.cpp
csrc/denoise_kernel.cu
diffusion_policy_accelerated/__init__.py
diffusion_policy_accelerated/config.py
diffusion_policy_accelerated/main.py
diffusion_policy_accelerated.egg-info/PKG-INFO
diffusion_policy_accelerated.egg-info/SOURCES.txt
diffusion_policy_accelerated.egg-info/dependency_links.txt
diffusion_policy_accelerated.egg-info/entry_points.txt
diffusion_policy_accelerated.egg-info/requires.txt
diffusion_policy_accelerated.egg-info/top_level.txt
diffusion_policy_accelerated/diffusion_policy/__init__.py
diffusion_policy_accelerated/diffusion_policy/eval.py
diffusion_policy_accelerated/diffusion_policy/model.py
diffusion_policy_accelerated/diffusion_policy/push_t_env.py
tests/test_conv1d_gnm.py
tests/test_denoise.py